pynsy/__init__.py
pynsy/main.py
pynsy/programmatic_usage.py
pynsy/analyses/__init__.py
pynsy/analyses/key_in_list_analysis.py
pynsy/analyses/shape_logger.py
pynsy/analyses/string_add_analysis.py
pynsy/instrumentation/__init__.py
pynsy/instrumentation/analyzer_handle.py
pynsy/instrumentation/heap_object_tracking.py
pynsy/instrumentation/instrument.py
pynsy/instrumentation/instrument_nested.py
pynsy/instrumentation/module_loader.py
pynsy/instrumentation/operator_apply.py
pynsy/instrumentation/util.py
pynsy-0.1.0.dist-info/LICENSE
pynsy-0.1.0.dist-info/WHEEL
pynsy-0.1.0.dist-info/METADATA
pynsy-0.1.0.dist-info/RECORD
