Metadata-Version: 2.1
Name: pynsy
Version: 0.1.0
Summary: A Python analysis framework.
Keywords: 
Author-email: Pynsy authors <pynsy-dev@google.com>
Requires-Python: >=3.7
Classifier: Programming Language :: Python :: 3
Classifier: Programming Language :: Python :: 3 :: Only
Classifier: License :: OSI Approved :: Apache Software License
Classifier: Intended Audience :: Science/Research
Classifier: Topic :: Software Development :: Libraries :: Python Modules
Requires-Dist: absl-py
Requires-Dist: bytecode
Requires-Dist: config
Requires-Dist: jax
Requires-Dist: jaxlib
Requires-Dist: numpy
Requires-Dist: mypy
Requires-Dist: pandas
Requires-Dist: typing_extensions
Requires-Dist: pytest ; extra == "dev"
Requires-Dist: pytest-xdist ; extra == "dev"
Requires-Dist: pylint>=2.6.0 ; extra == "dev"
Requires-Dist: pyink ; extra == "dev"
Project-URL: changelog, https://github.com/google-research/pynsy/blob/main/CHANGELOG.md
Project-URL: homepage, https://github.com/google-research/pynsy
Project-URL: repository, https://github.com/google-research/pynsy
Provides-Extra: dev
